odoo9_addon_l10n_es_aeat_mod216-9.0.1.0.0-py2.7-nspkg.pth
odoo9_addon_l10n_es_aeat_mod216-9.0.1.0.0.dist-info/DESCRIPTION.rst
odoo9_addon_l10n_es_aeat_mod216-9.0.1.0.0.dist-info/METADATA
odoo9_addon_l10n_es_aeat_mod216-9.0.1.0.0.dist-info/RECORD
odoo9_addon_l10n_es_aeat_mod216-9.0.1.0.0.dist-info/WHEEL
odoo9_addon_l10n_es_aeat_mod216-9.0.1.0.0.dist-info/metadata.json
odoo9_addon_l10n_es_aeat_mod216-9.0.1.0.0.dist-info/namespace_packages.txt
odoo9_addon_l10n_es_aeat_mod216-9.0.1.0.0.dist-info/top_level.txt
odoo_addons/l10n_es_aeat_mod216/README.rst
odoo_addons/l10n_es_aeat_mod216/__init__.py
odoo_addons/l10n_es_aeat_mod216/__openerp__.py
odoo_addons/l10n_es_aeat_mod216/data/aeat_export_mod216_data.xml
odoo_addons/l10n_es_aeat_mod216/data/tax_code_map_mod216_data.xml
odoo_addons/l10n_es_aeat_mod216/docs/DR-216e16_v1.06.pdf
odoo_addons/l10n_es_aeat_mod216/i18n/bg.po
odoo_addons/l10n_es_aeat_mod216/i18n/cs.po
odoo_addons/l10n_es_aeat_mod216/i18n/es.po
odoo_addons/l10n_es_aeat_mod216/i18n/es_CO.po
odoo_addons/l10n_es_aeat_mod216/i18n/es_CR.po
odoo_addons/l10n_es_aeat_mod216/i18n/eu.po
odoo_addons/l10n_es_aeat_mod216/i18n/fr.po
odoo_addons/l10n_es_aeat_mod216/i18n/gl.po
odoo_addons/l10n_es_aeat_mod216/i18n/hr.po
odoo_addons/l10n_es_aeat_mod216/i18n/nl.po
odoo_addons/l10n_es_aeat_mod216/i18n/pl.po
odoo_addons/l10n_es_aeat_mod216/i18n/pt.po
odoo_addons/l10n_es_aeat_mod216/i18n/pt_BR.po
odoo_addons/l10n_es_aeat_mod216/i18n/ru.po
odoo_addons/l10n_es_aeat_mod216/i18n/sl.po
odoo_addons/l10n_es_aeat_mod216/i18n/sv.po
odoo_addons/l10n_es_aeat_mod216/i18n/tr.po
odoo_addons/l10n_es_aeat_mod216/i18n/vi.po
odoo_addons/l10n_es_aeat_mod216/models/__init__.py
odoo_addons/l10n_es_aeat_mod216/models/mod111.py
odoo_addons/l10n_es_aeat_mod216/models/mod216.py
odoo_addons/l10n_es_aeat_mod216/models/res_partner.py
odoo_addons/l10n_es_aeat_mod216/security/ir.model.access.csv
odoo_addons/l10n_es_aeat_mod216/static/description/icon.png
odoo_addons/l10n_es_aeat_mod216/static/description/icon_source.svg
odoo_addons/l10n_es_aeat_mod216/tests/__init__.py
odoo_addons/l10n_es_aeat_mod216/tests/test_l10n_es_aeat_mod216.py
odoo_addons/l10n_es_aeat_mod216/views/mod216_view.xml
odoo_addons/l10n_es_aeat_mod216/views/res_partner_view.xml
